repo_downloader/__init__.py
repo_downloader/main.py
repo_downloader-0.1.11.dist-info/METADATA
repo_downloader-0.1.11.dist-info/WHEEL
repo_downloader-0.1.11.dist-info/entry_points.txt
repo_downloader-0.1.11.dist-info/licenses/LICENSE
repo_downloader-0.1.11.dist-info/RECORD
