Metadata-Version: 2.3
Name: repo-downloader
Version: 0.1.11
Summary: A CLI tool to download files from a Git repository into a zipped directory.
Author-email: Alex Meyer <acomeyer@gmail.com>
License-File: LICENSE
Classifier: License :: OSI Approved :: MIT License
Classifier: Operating System :: OS Independent
Classifier: Programming Language :: Python :: 3
Requires-Python: >=3.7
Requires-Dist: click
Requires-Dist: gitpython
Provides-Extra: dev
Requires-Dist: black; extra == 'dev'
Requires-Dist: flake8; extra == 'dev'
Requires-Dist: pytest; extra == 'dev'
